{
    "Enemy": {
        "checkpoints": [
            {
                "steps": 7999970,
                "file_path": "results\\TrainingEnemy\\Enemy\\Enemy-7999970.onnx",
                "reward": null,
                "creation_time": 1682011475.9901428,
                "auxillary_file_paths": [
                    "results\\TrainingEnemy\\Enemy\\Enemy-7999970.pt"
                ]
            },
            {
                "steps": 8499974,
                "file_path": "results\\TrainingEnemy\\Enemy\\Enemy-8499974.onnx",
                "reward": null,
                "creation_time": 1682014501.458687,
                "auxillary_file_paths": [
                    "results\\TrainingEnemy\\Enemy\\Enemy-8499974.pt"
                ]
            },
            {
                "steps": 8999990,
                "file_path": "results\\TrainingEnemy\\Enemy\\Enemy-8999990.onnx",
                "reward": 0.0,
                "creation_time": 1682017395.2074845,
                "auxillary_file_paths": [
                    "results\\TrainingEnemy\\Enemy\\Enemy-8999990.pt"
                ]
            },
            {
                "steps": 9499963,
                "file_path": "results\\TrainingEnemy\\Enemy\\Enemy-9499963.onnx",
                "reward": null,
                "creation_time": 1682020295.962819,
                "auxillary_file_paths": [
                    "results\\TrainingEnemy\\Enemy\\Enemy-9499963.pt"
                ]
            },
            {
                "steps": 9570042,
                "file_path": "results\\TrainingEnemy\\Enemy\\Enemy-9570042.onnx",
                "reward": null,
                "creation_time": 1682020767.3909533,
                "auxillary_file_paths": [
                    "results\\TrainingEnemy\\Enemy\\Enemy-9570042.pt"
                ]
            }
        ],
        "final_checkpoint": {
            "steps": 9570042,
            "file_path": "results\\TrainingEnemy\\Enemy.onnx",
            "reward": null,
            "creation_time": 1682020767.3909533,
            "auxillary_file_paths": [
                "results\\TrainingEnemy\\Enemy\\Enemy-9570042.pt"
            ]
        }
    },
    "metadata": {
        "stats_format_version": "0.3.0",
        "mlagents_version": "0.26.0",
        "torch_version": "1.7.1+cu110"
    }
}